{
  "X": [
    -0.1309,
    0.0647,
    -0.0417,
    0.0687,
    -0.0281,
    0.1212,
    -0.2526,
    0.481,
    -0.294,
    0.146,
    -0.1336,
    -0.3088,
    -0.1626,
    0.2994,
    -0.1629,
    -0.201,
    -0.108,
    0.1817,
    0.4615,
    0.2878,
    0.413,
    0.5419,
    -0.2916,
    0.1065,
    -0.476,
    0.1878,
    -0.3077
  ],
  "Y": [
    -0.1843,
    -0.0649,
    0.1578,
    0.1847,
    0.2164,
    -0.1047,
    -0.0422,
    -0.1948,
    -0.1098,
    0.0483,
    0.0652,
    0.0226,
    -0.1594,
    -0.0998,
    0.0237,
    -0.0077,
    0.1152,
    -0.0329,
    0.1665,
    0.1235,
    0.0349,
    -0.4564,
    0.2067,
    0.3053,
    -0.5603,
    0.4169,
    0.3894
  ],
  "Z": {},
  "label": [
    "Bureaucratic",
    "Slow service",
    "Friendly",
    "Low prices",
    "Fashionable",
    "Unfashionable",
    "Reliable",
    "Here today, gone tomorrow",
    "Good coverage",
    "Network often down",
    "The best phones",
    "Conveniently located stores",
    "High prices",
    "Unreliable",
    "Meet all my communication needs",
    "Leaders in mobile phone technology",
    "I like them",
    "I hate them",
    "Don't know much about them",
    "AAPT/Cellular One",
    "New Tel",
    "One-tel",
    "Optus",
    "Orange (Hutchison)",
    "Telstra (Mobile Net)",
    "Virgin Mobile",
    "Vodafone"
  ],
  "labelAlt": {},
  "group": [
    "Rows",
    "Rows",
    "Rows",
    "Rows",
    "Rows",
    "Rows",
    "Rows",
    "Rows",
    "Rows",
    "Rows",
    "Rows",
    "Rows",
    "Rows",
    "Rows",
    "Rows",
    "Rows",
    "Rows",
    "Rows",
    "Rows",
    "Columns",
    "Columns",
    "Columns",
    "Columns",
    "Columns",
    "Columns",
    "Columns",
    "Columns"
  ],
  "fixedAspectRatio": true,
  "colors": [
    "#4472C4",
    "#FFC000"
  ],
  "xTitle": "Component 1 (60.3%)",
  "yTitle": "Component 2 (17.6%)",
  "title": "Principal Components Analysis Biplot",
  "titleFontSize": 20,
  "labelsFontColor": null,
  "labelsFontSize": 12,
  "labelsLogoScale": null,
  "yTitleFontSize": 16,
  "xTitleFontSize": 16,
  "axisFontSize": 10,
  "pointRadius": 2
}