{
  "X": [
    0,
    1,
    2,
    3,
    4,
    5,
    6,
    7,
    8,
    9,
    10,
    11,
    12,
    13,
    14,
    15,
    16,
    17,
    18,
    19
  ],
  "Y": [
    0,
    0,
    0,
    0,
    0,
    0,
    0,
    0,
    0,
    0,
    0,
    0,
    0,
    0,
    0,
    0,
    0,
    0,
    0,
    0
  ],
  "Z": [
    0,
    1,
    2,
    3,
    4,
    5,
    6,
    7,
    8,
    9,
    10,
    11,
    12,
    13,
    14,
    15,
    16,
    17,
    18,
    19
  ],
  "label": [
    "t",
    "s",
    "r",
    "q",
    "p",
    "o",
    "n",
    "m",
    "l",
    "k",
    "j",
    "i",
    "h",
    "g",
    "f",
    "e",
    "d",
    "c",
    "b",
    "a"
  ],
  "origin": false,
  "grid": false,
  "legendShow": false,
  "legendBubblesShow": false,
  "transparency": 0.4,
  "showXAxis": false,
  "yBoundsMinimum": -0.25,
  "yBoundsMaximum": 0.25
}